pixeldifference/__init__.py
pixeldifference/pixeldifference.py
pixeldifference-1.0.0.dist-info/LICENSE
pixeldifference-1.0.0.dist-info/METADATA
pixeldifference-1.0.0.dist-info/WHEEL
pixeldifference-1.0.0.dist-info/top_level.txt
pixeldifference-1.0.0.dist-info/RECORD
