Metadata-Version: 2.1
Name: pixeldifference
Version: 1.0.0
Summary: Get the total RGB or hexadecimal pixel differences between two images.
Home-page: https://github.com/pbiswell/pixeldifference
Author: Paul Biswell
Author-email: pblabsdev@gmail.com
License: UNKNOWN
Keywords: pixeldifference,image-pixel-difference,pixel,image,compare,pixels,RGB,hex,hexadecimal
Platform: UNKNOWN
Classifier: Development Status :: 5 - Production/Stable
Classifier: Intended Audience :: Developers
Classifier: Intended Audience :: System Administrators
Classifier: Intended Audience :: Education
Classifier: Programming Language :: Python
Classifier: Programming Language :: Python :: 3
Classifier: Operating System :: MacOS :: MacOS X
Classifier: Operating System :: Microsoft :: Windows
Classifier: Operating System :: POSIX
Classifier: License :: OSI Approved :: Apache Software License
Classifier: Natural Language :: English
Classifier: Operating System :: OS Independent
Classifier: Topic :: Education
Classifier: Topic :: Multimedia :: Graphics
License-File: LICENSE
Requires-Dist: pillow
